[
  {
    "url": "www.ntnu.no",
    "institusjon": "universitet"
  },
  {
    "url": "www.nmbu.no",
    "institusjon": "universitet"
  },
  {
   "url": "www.uib.no",
    "institusjon": "universitet"
  },
  {
    "url": "www.uis.no",
    "institusjon": "universitet"
  },
  {
    "url": "www.uit.no",
    "institusjon": "universitet"
  },
  {
    "url": "www.uia.no",
    "institusjon": "universitet"
  },
  {
    "url": "www.nord.no",
    "institusjon": "universitet"
  },
  {
    "url": "www.hioa.no",
    "institusjon": "universitet"
  },
  {
    "url": "www.usn.no",
    "institusjon": "universitet"
  },
  {
    "url": "www.aho.no",
    "institusjon": "vitenskapelig høyskole"
  },
  {
    "url": "www.khio.no",
    "institusjon": "vitenskapelig høyskole"
  },
  {
    "url": "www.nhh.no",
    "institusjon": "vitenskapelig høyskole"
  },
  {
    "url": "www.nih.no",
    "institusjon": "vitenskapelig høyskole"
  },
  {
    "url": "www.nmh.no",
    "institusjon": "vitenskapelig høyskole"
  },
  {
    "url": "www.himolde.no",
    "institusjon": "vitenskapelig høyskole"
  },
  {
    "url": "www.samiskhs.no",
    "institusjon": "statlig høyskole"
  },
  {
    "url": "www.hvl.no",
    "institusjon": "statlig høyskole"
  },
  {
    "url": "www.hihhm.no",
    "institusjon": "statlig høyskole"
  },
  {
    "url": "hivolda.no",
    "institusjon": "statlig høyskole"
  },
  {
    "url": "www.hiof.no",
    "institusjon": "statlig høyskole"
  }
]